{
    "notifications": {
        "id": "Webhook ID",
        "token": "Webhook token"
    },
    "etf": {
        "username": "ETF username",
        "password": "ETF password"
    },
    "interval": 30000,
    "relays": [
        {
            "type": "labvezbe",
            "id": "Webhook ID",
            "token": "Webhook token",
            "regex": "OOP?1|oop?1|ORT2|ort2|BP1|bp1",
            "autoSignup": true
        },
        {
            "type": "domaci",
            "id": "Webhook ID 2",
            "token":"Webhook token 2",
            "regex": "OOP?1|oop?1|ORT2|ort2|BP1|bp1"
        }
    ]
}
